tabadul/__init__.py
tabadul/base.py
tabadul/client.py
tabadul/configuration.py
tabadul/exceptions/__init__.py
tabadul/exceptions/api_exception.py
tabadul/handlers/__init__.py
tabadul/handlers/handler.py
tabadul/handlers/declaration_fees/__init__.py
tabadul/handlers/declaration_fees/des_fees.py
tabadul/handlers/demurrage/__init__.py
tabadul/handlers/demurrage/send_import_demurrage_fees.py
tabadul/handlers/demurrage/send_transhipment_demurrage_fees.py
tabadul/helpers/__init__.py
tabadul/helpers/api_helper.py
tabadul/http/__init__.py
tabadul/http/http_client.py
tabadul/http/http_context.py
tabadul/http/http_method_enum.py
tabadul/http/http_request.py
tabadul/http/http_response.py
tabadul/http/requests_client.py
tabadul/http/auth/__init__.py
tabadul/http/auth/api_token.py
tabadul/requests/__init__.py
tabadul/requests/declaration_fees/__init__.py
tabadul/requests/declaration_fees/des_fees.py
tabadul/requests/demurrage/__init__.py
tabadul/requests/demurrage/send_import_demurrage_fees.py
tabadul/requests/demurrage/send_import_excemptions_info.py
tabadul/requests/demurrage/send_transhipment_demurrage_fees.py
tabadul/responses/__init__.py
tabadul/responses/declaration_fees/__init__.py
tabadul/responses/declaration_fees/des_fees.py
tabadul/responses/demurrage/__init__.py
tabadul/responses/demurrage/send_import_demurrage_fees.py
tabadul/responses/demurrage/send_import_excemptions_info.py
tabadul/responses/demurrage/send_transhipment_demurrage_fees.py
tabadul-1.0.1.dist-info/licenses/LICENSE.txt
tests/__init__.py
tabadul-1.0.1.dist-info/METADATA
tabadul-1.0.1.dist-info/WHEEL
tabadul-1.0.1.dist-info/top_level.txt
tabadul-1.0.1.dist-info/RECORD
