Metadata-Version: 2.4
Name: tabadul
Version: 1.0.1
Summary: Tabadul API client
Home-page: https://gitlab.com/abdroos/tabadul
Author: Abdullah Alaidrous
Author-email: abd.alaidrous@gmail.com
Classifier: Programming Language :: Python :: 3
Classifier: License :: OSI Approved :: MIT License
Classifier: Operating System :: OS Independent
Requires-Python: >=3.6
License-File: LICENSE.txt
Requires-Dist: requests>=2.32.3
Requires-Dist: python-dateutil>=2.8.2
Requires-Dist: jsonpickle>=0.9.6
Requires-Dist: urllib3>=1.26.20
Requires-Dist: six>=1.16.0
Dynamic: author
Dynamic: author-email
Dynamic: classifier
Dynamic: description
Dynamic: description-content-type
Dynamic: home-page
Dynamic: license-file
Dynamic: requires-dist
Dynamic: requires-python
Dynamic: summary
